{
  "project_info": {
    "project_number": "162206017185",
    "firebase_url": "https://hercules-68e66.firebaseio.com",
    "project_id": "hercules-68e66",
    "storage_bucket": "hercules-68e66.appspot.com"
  },
  "client": [
    {
      "client_info": {
        "mobilesdk_app_id": "1:162206017185:android:c19a26e9c99c0a80b632e0",
        "android_client_info": {
          "package_name": "basam.example.com.hercules"
        }
      },
      "oauth_client": [
        {
          "client_id": "162206017185-s35hijkgqfb642l8hque87d6ri7cmksl.apps.googleusercontent.com",
          "client_type": 3
        }
      ],
      "api_key": [
        {
          "current_key": "AIzaSyAvIEXMpou2xkvUonL_3t0ABmXX9YgU8bQ"
        }
      ],
      "services": {
        "appinvite_service": {
          "other_platform_oauth_client": [
            {
              "client_id": "162206017185-s35hijkgqfb642l8hque87d6ri7cmksl.apps.googleusercontent.com",
              "client_type": 3
            }
          ]
        }
      }
    }
  ],
  "configuration_version": "1"
}